batch_runner/__init__.py
batch_runner/config.py
batch_runner/manager.py
batch_runner/runner.py
hamtaa_batch_runner-0.0.0.dist-info/licenses/LICENSE
hamtaa_batch_runner-0.0.0.dist-info/METADATA
hamtaa_batch_runner-0.0.0.dist-info/WHEEL
hamtaa_batch_runner-0.0.0.dist-info/top_level.txt
hamtaa_batch_runner-0.0.0.dist-info/RECORD
