Metadata-Version: 2.4
Name: hamtaa-batch-runner
Version: 0.0.0
Summary: A tool to process large datasets using OpenAI's batch API
Author-email: Givechi <mohamad.m.givechi@gmail.com>, Tohidi <the.mohammad.tohidi@gmail.com>, Erfan Moosavi <erfanmoosavi84@gmail.com>
License: MIT
Keywords: nlp,llm,text-processing,openai
Requires-Python: >=3.9
License-File: LICENSE
Requires-Dist: openai>=1.97.1
Requires-Dist: pydantic>=2.0.0
Dynamic: license-file
